cdktf_cdktf_provider_hcp/__init__.py
cdktf_cdktf_provider_hcp/py.typed
cdktf_cdktf_provider_hcp/_jsii/__init__.py
cdktf_cdktf_provider_hcp/_jsii/provider-hcp@10.4.0.jsii.tgz
cdktf_cdktf_provider_hcp/aws_network_peering/__init__.py
cdktf_cdktf_provider_hcp/aws_transit_gateway_attachment/__init__.py
cdktf_cdktf_provider_hcp/azure_peering_connection/__init__.py
cdktf_cdktf_provider_hcp/boundary_cluster/__init__.py
cdktf_cdktf_provider_hcp/consul_cluster/__init__.py
cdktf_cdktf_provider_hcp/consul_cluster_root_token/__init__.py
cdktf_cdktf_provider_hcp/consul_snapshot/__init__.py
cdktf_cdktf_provider_hcp/data_hcp_aws_network_peering/__init__.py
cdktf_cdktf_provider_hcp/data_hcp_aws_transit_gateway_attachment/__init__.py
cdktf_cdktf_provider_hcp/data_hcp_azure_peering_connection/__init__.py
cdktf_cdktf_provider_hcp/data_hcp_boundary_cluster/__init__.py
cdktf_cdktf_provider_hcp/data_hcp_consul_agent_helm_config/__init__.py
cdktf_cdktf_provider_hcp/data_hcp_consul_agent_kubernetes_secret/__init__.py
cdktf_cdktf_provider_hcp/data_hcp_consul_cluster/__init__.py
cdktf_cdktf_provider_hcp/data_hcp_consul_versions/__init__.py
cdktf_cdktf_provider_hcp/data_hcp_dns_forwarding/__init__.py
cdktf_cdktf_provider_hcp/data_hcp_dns_forwarding_rule/__init__.py
cdktf_cdktf_provider_hcp/data_hcp_group/__init__.py
cdktf_cdktf_provider_hcp/data_hcp_hvn/__init__.py
cdktf_cdktf_provider_hcp/data_hcp_hvn_peering_connection/__init__.py
cdktf_cdktf_provider_hcp/data_hcp_hvn_route/__init__.py
cdktf_cdktf_provider_hcp/data_hcp_iam_policy/__init__.py
cdktf_cdktf_provider_hcp/data_hcp_organization/__init__.py
cdktf_cdktf_provider_hcp/data_hcp_packer_artifact/__init__.py
cdktf_cdktf_provider_hcp/data_hcp_packer_bucket_names/__init__.py
cdktf_cdktf_provider_hcp/data_hcp_packer_run_task/__init__.py
cdktf_cdktf_provider_hcp/data_hcp_packer_version/__init__.py
cdktf_cdktf_provider_hcp/data_hcp_private_link/__init__.py
cdktf_cdktf_provider_hcp/data_hcp_project/__init__.py
cdktf_cdktf_provider_hcp-10.4.0.dist-info/LICENSE
cdktf_cdktf_provider_hcp-10.4.0.dist-info/METADATA
cdktf_cdktf_provider_hcp-10.4.0.dist-info/WHEEL
cdktf_cdktf_provider_hcp-10.4.0.dist-info/top_level.txt
cdktf_cdktf_provider_hcp-10.4.0.dist-info/RECORD
